Workbook

Sheet TARIFICACIÓN
B2: TIPO DE VH | C2: TIEMPO DE CRÉDITO | D2: RIESGO MARCAS | E2: RIESGO CIUDADES | F2: RIESGO GENERO | G2: RIESGO USO | H2: DEPRECIACIÓN | I2: TASA
B3: VH USADOS Y NUEVOS LIVIANOS PARTICULARES | C3: HASTA 2 AÑOS | D3: 1 | E3: 1 | F3: 1 | G3: 1 | H3: 0.18 | I3: 0.036
B4: VH USADOS Y NUEVOS LIVIANOS PARTICULARES | C4: HASTA 2 AÑOS | D4: 2 | E4: 2 | F4: 2 | G4: 2 | H4: 0.15 | I4: 0.034
B5: VH USADOS Y NUEVOS LIVIANOS PARTICULARES | C5: HASTA 2 AÑOS | D5: 3 | E5: 3 | F5: 3 | G5: 3 | H5: 0.1 | I5: 0.032
B6: VH USADOS Y NUEVOS LIVIANOS PARTICULARES | C6: HASTA 3 A 5 AÑOS | D6: 1 | E6: 1 | F6: 1 | G6: 1 | H6: 0.18 | I6: 0.035
B7: VH USADOS Y NUEVOS LIVIANOS PARTICULARES | C7: HASTA 3 A 5 AÑOS | D7: 2 | E7: 2 | F7: 2 | G7: 2 | H7: 0.15 | I7: 0.033
B8: VH USADOS Y NUEVOS LIVIANOS PARTICULARES | C8: HASTA 3 A 5 AÑOS | D8: 3 | E8: 3 | F8: 3 | G8: 3 | H8: 0.1 | I8: 0.031
B9: VH LIVIANOS NUEVOS Y USADOS ALTA GAMA (40.000.00 EN ADELANTE) | C9: DE 1 A 5 AÑOS | D9: 1 | E9: 1 | F9: 1 | G9: 1 | H9: 0.15 | I9: 0.029
B10: VH LIVIANOS NUEVOS Y USADOS ALTA GAMA (40.000.00 EN ADELANTE) | C10: DE 1 A 5 AÑOS | D10: 2 | E10: 2 | F10: 2 | G10: 2 | H10: 0.15 | I10: 0.027
B11: VH LIVIANOS NUEVOS Y USADOS ALTA GAMA (40.000.00 EN ADELANTE) | C11: DE 1 A 5 AÑOS | D11: 3 | E11: 3 | F11: 3 | G11: 3 | H11: 0.15 | I11: 0.025
B12: VH DE ALQUILER | C12: DE 1 A 5 AÑOS | D12: 1 | E12: 1 | F12: 1 | G12: 1 | H12: 0.18 | I12: 0.049
B13: VH DE ALQUILER | C13: DE 1 A 5 AÑOS | D13: 2 | E13: 2 | F13: 2 | G13: 1 | H13: 0.15 | I13: 0.046
B14: VH DE ALQUILER | C14: DE 1 A 5 AÑOS | D14: 3 | E14: 3 | F14: 3 | G14: 1 | H14: 0.12 | I14: 0.044

Sheet COTIZACIÓN
R7: GENERO | S7: USO | T7: MODELO | U7: ESTADO CIVIL | V7: TIEMPO CREDITO | W7: COLOR | X7: TIEMPO CREDITO | Y7: ESTADO DEL VH
R8: HOMBRE | S8: COMERCIAL | T8: Chevrolet Sail | U8: SOLTERO/A | V8: 1 | W8: NEGRO | X8: =IF(OR(G22=1, G22=2), "HASTA 2 AÑOS", IF(OR(G22=3, G22=4, G22=5), "HASTA 3 A 5 AÑOS", "Valor no válido")) -> HASTA 3 A 5 AÑOS | Y8: NUEVO
R9: MUJER | S9: PARTICULAR | T9: Chevrolet Aveo | U9: CASADO/A | V9: 2 | W9: AMARILLO TAXI | Y9: USADO
C10: NOMBRE | D10: JUANITO | F10: MARCA | G10: Chevrolet Aveo | I10: TASA | K10: CUOTA | R10: TERCERA EDAD | S10: CORPORATIVO | T10: Chevrolet D-Max | V10: 3 | W10: MARRON
I11: =AVERAGE(P12:P20) -> 0.035555556 | K11: ='MODELO MENSUALIZADO'!K5 -> 101.76804 | T11: Grand Vitara | V11: 4 | W11: AZUL
C12: ESTADO CIVIL | D12: CASADO/A | F12: MODELO | G12: AMAROK | P12: =INDEX(PARAMETRIZACIÓN!B9:B11,MATCH("*"&G12&"*",PARAMETRIZACIÓN!E9:E11,0)) -> 0.042 | T12: Kia Sportage | V12: 5 | W12: VERDE
P13: =INDEX(PARAMETRIZACIÓN!B9:B11,MATCH("*"&G16&"*",PARAMETRIZACIÓN!I9:I11,0)) -> 0.036 | T13: Hyundai Tucson | W13: ROJO
C14: EDAD | D14: 50 | F14: COLOR | G14: PLATA | I14: RIESGO | J14: =IF(P27=1,"ALTO",IF(P27=2,"MODERADO","BAJO")) -> ALTO | P14: =INDEX(PARAMETRIZACIÓN!B9:B11,MATCH("*"&D16&"*",PARAMETRIZACIÓN!G9:G11,0)) -> 0.042 | T14: Hyundai Accent | W14: GRIS OSCURO
P15: =INDEX(PARAMETRIZACIÓN!B9:B11,MATCH("*"&D18&"*",PARAMETRIZACIÓN!H9:H11,0)) -> 0.042 | T15: Kia Rio | W15: BLANCO
C16: CIUDAD | D16: MANTA | F16: USO | G16: PARTICULAR | P16: =INDEX(PARAMETRIZACIÓN!B9:B11,MATCH("*"&G14&"*",PARAMETRIZACIÓN!J9:J11,0)) -> 0.029 | T16: Nissan Sentra | W16: PLATA
P17: =INDEX(PARAMETRIZACIÓN!B9:B11,MATCH("*"&D12&"*",PARAMETRIZACIÓN!K9:K11,0)) -> 0.036 | T17: Suzuki Vitara SZ
C18: GÉNERO | D18: HOMBRE | F18: ESTADO DEL VH | G18: USADO | P18: =IF(D14<25,PARAMETRIZACIÓN!B9,IF(D14<45,PARAMETRIZACIÓN!B10,PARAMETRIZACIÓN!B11)) -> 0.029 | T18: Mitsubishi Montero
P19: =IF(G20<20000,PARAMETRIZACIÓN!B9,IF(G20<30000,PARAMETRIZACIÓN!B10,PARAMETRIZACIÓN!B11)) -> 0.029 | T19: MAZDA BT50
F20: VALOR ASEGURADO | G20: 40000 | P20: {=SUMPRODUCT((PARAMETRIZACIÓN!C17:C22=X8)*(PARAMETRIZACIÓN!D17:D22=P27)*(PARAMETRIZACIÓN!B17:B22))} -> 0.035 | T20: AMAROK
T21: F150
F22: AÑOS DE SEGURO | G22: 4 | T22: Volkswagen T-Cross
T23: Volkswagen Nuevo Virtus
T24: Volkswagen Nivus
T25: Toyota Corolla
T26: Nissan Qashqai
P27: =INDEX(PARAMETRIZACIÓN!D9:D11,MATCH("*"&G12&"*",PARAMETRIZACIÓN!E9:E11,0)) -> 1 | T27: Mistubishi Outlander
C28: PÉRDIDAS PARCIALES | D28: =INDEX(PARAMETRIZACIÓN!C35:C37,MATCH("*"&J14&"*",PARAMETRIZACIÓN!B35:B37,0)) -> 20% DEL VALOR DEL SINIESTRO MÍNIMO 700 | T28: KIA K3
T29: K3 Cross
C30: PÉRDIDAS TOTALES | D30: =INDEX(PARAMETRIZACIÓN!D35:D37,MATCH("*"&J14&"*",PARAMETRIZACIÓN!B35:B37,0)) -> 20% DEL VALOR ASEGURADO | T30: Chevrolet Tracker
T31: Volvo
T32: BMW
T33: Mercedes-Benz
T34: Audi
T35: HONDA
T36: SUBARU
T37: BYD
T38: GEELY
T39: Volkswagen Passat
T40: Mazda CX-80
T41: Audi Q6 e-tron
T42: Zeekr X
T43: Maxus eTERRON 9

Sheet MODELO MENSUALIZADO
B1: NOMBRE DEL ASEGURADO: | D1: HORNA GONZALES JEYDY ESTHER
B2: VEHICULO: | D2: GREAT WALL
B3: AÑOS DE VIGENCIA | D3: =COTIZACIÓN!G22 -> 4
B5: AÑOS | C5: DEPRECIACIÓN AUTOS NUEVOS | D5: DEPRECIACIÓN AUTOS USADOS | E5: VALORES ASEGURADOS | F5: VALOR ANUAL DE DEPRECIACIÓN | G5: VALOR ANUAL DE DEPRECIACIÓN MENSUAL | H5: TASA | J5: CUOTA FIJA (pago cliente) | K5: =AVERAGE(J14:J61) -> 101.76804
B6: 1er. Año | C6: =PARAMETRIZACIÓN!C27 -> 0.1 | D6: =PARAMETRIZACIÓN!C29 -> 0.15 | E6: =+COTIZACIÓN!G20 -> 40000 | F6: =IF(COTIZACIÓN!G18="NUEVO",'MODELO MENSUALIZADO'!E6*'MODELO MENSUALIZADO'!C6,'MODELO MENSUALIZADO'!E6*'MODELO MENSUALIZADO'!D6) -> 6000 | G6: =+F6/12 -> 500 | H6: =+COTIZACIÓN!I11 -> 0.035555556
B7: 2do. Año | C7: =PARAMETRIZACIÓN!C28 -> 0.15 | D7: =PARAMETRIZACIÓN!C30 -> 0.18 | E7: =+E6-F6 -> 34000 | F7: =IF(COTIZACIÓN!G19="NUEVO",'MODELO MENSUALIZADO'!E7*'MODELO MENSUALIZADO'!C7,'MODELO MENSUALIZADO'!E7*'MODELO MENSUALIZADO'!D7) -> 6120 | G7: =+F7/12 -> 510 | H7: 0.0352
B8: 3er. Año | C8: =PARAMETRIZACIÓN!C28 -> 0.15 | D8: =PARAMETRIZACIÓN!C30 -> 0.18 | E8: =+E7-F7 -> 27880 | F8: =IF(COTIZACIÓN!G20="NUEVO",'MODELO MENSUALIZADO'!E8*'MODELO MENSUALIZADO'!C8,'MODELO MENSUALIZADO'!E8*'MODELO MENSUALIZADO'!D8) -> 5018.4 | G8: =+F8/12 -> 418.2 | H8: 0.0352
B9: 4to. Año | C9: =PARAMETRIZACIÓN!C28 -> 0.15 | D9: =PARAMETRIZACIÓN!C30 -> 0.18 | E9: =+E8-F8 -> 22861.6 | F9: =IF(COTIZACIÓN!G21="NUEVO",'MODELO MENSUALIZADO'!E9*'MODELO MENSUALIZADO'!C9,'MODELO MENSUALIZADO'!E9*'MODELO MENSUALIZADO'!D9) -> 4115.088 | G9: =+F9/12 -> 342.924 | H9: 0.0352
B10: 5to. Año | C10: =PARAMETRIZACIÓN!C28 -> 0.15 | D10: =PARAMETRIZACIÓN!C30 -> 0.18 | E10: =+E9-F9 -> 18746.512 | F10: =IF(COTIZACIÓN!G22="NUEVO",'MODELO MENSUALIZADO'!E10*'MODELO MENSUALIZADO'!C10,'MODELO MENSUALIZADO'!E10*'MODELO MENSUALIZADO'!D10) -> 3374.3722 | G10: =+F10/12 -> 281.19768 | H10: 0.0352
E12: 0.035 | F12: 0.005 | G12: 0.5 | I12: 0.15 | M12: NIVELACIÓN
B13: MES | C13: VALOR ASEGURADO | D13: PRIMA NETA MES | E13: SUPER DE BANCOS | F13: SEGURO CAMPESINO | G13: DERECHOS DE EMISIÓN | H13: SUBTOTAL | I13: IVA | J13: PRIMA TOTAL MES (COSTO REAL) | M13: CUOTA FIJA | N13: DIFERENCIA | O13: NIVELACIÓN ACUMULADA
B14: 1 | C14: =+E6 -> 40000 | D14: =+C14*($H$6/12) -> 118.51852 | E14: =+D14*$E$12 -> 4.1481481 | F14: =+D14*$F$12 -> 0.59259259 | G14: =+$G$12 -> 0.5 | H14: =+SUM(D14:G14) -> 123.75926 | I14: =+H14*$I$12 -> 18.563889 | J14: =+H14+I14 -> 142.32315 | M14: =$K$5 -> 101.76804 | N14: =M14-J14 -> -40.555107 | O14: =+N14 -> -40.555107
B15: 2 | C15: =+C14-G$6 -> 39500 | D15: =+C15*($H$6/12) -> 117.03704 | E15: =+D15*$E$12 -> 4.0962963 | F15: =+D15*$F$12 -> 0.58518519 | G15: =+$G$12 -> 0.5 | H15: =+SUM(D15:G15) -> 122.21852 | I15: =+H15*$I$12 -> 18.332778 | J15: =+H15+I15 -> 140.5513 | M15: =$K$5 -> 101.76804 | N15: =M15-J15 -> -38.783256 | O15: =+O14+N15 -> -79.338363
B16: 3 | C16: =+C15-G$6 -> 39000 | D16: =+C16*($H$6/12) -> 115.55556 | E16: =+D16*$E$12 -> 4.0444444 | F16: =+D16*$F$12 -> 0.57777778 | G16: =+$G$12 -> 0.5 | H16: =+SUM(D16:G16) -> 120.67778 | I16: =+H16*$I$12 -> 18.101667 | J16: =+H16+I16 -> 138.77944 | M16: =$K$5 -> 101.76804 | N16: =M16-J16 -> -37.011404 | O16: =+O15+N16 -> -116.34977
B17: 4 | C17: =+C16-G$6 -> 38500 | D17: =+C17*($H$6/12) -> 114.07407 | E17: =+D17*$E$12 -> 3.9925926 | F17: =+D17*$F$12 -> 0.57037037 | G17: =+$G$12 -> 0.5 | H17: =+SUM(D17:G17) -> 119.13704 | I17: =+H17*$I$12 -> 17.870556 | J17: =+H17+I17 -> 137.00759 | M17: =$K$5 -> 101.76804 | N17: =M17-J17 -> -35.239552 | O17: =+O16+N17 -> -151.58932
B18: 5 | C18: =+C17-G$6 -> 38000 | D18: =+C18*($H$6/12) -> 112.59259 | E18: =+D18*$E$12 -> 3.9407407 | F18: =+D18*$F$12 -> 0.56296296 | G18: =+$G$12 -> 0.5 | H18: =+SUM(D18:G18) -> 117.5963 | I18: =+H18*$I$12 -> 17.639444 | J18: =+H18+I18 -> 135.23574 | M18: =$K$5 -> 101.76804 | N18: =M18-J18 -> -33.4677 | O18: =+O17+N18 -> -185.05702
B19: 6 | C19: =+C18-G$6 -> 37500 | D19: =+C19*($H$6/12) -> 111.11111 | E19: =+D19*$E$12 -> 3.8888889 | F19: =+D19*$F$12 -> 0.55555556 | G19: =+$G$12 -> 0.5 | H19: =+SUM(D19:G19) -> 116.05556 | I19: =+H19*$I$12 -> 17.408333 | J19: =+H19+I19 -> 133.46389 | M19: =$K$5 -> 101.76804 | N19: =M19-J19 -> -31.695848 | O19: =+O18+N19 -> -216.75287
B20: 7 | C20: =+C19-G$6 -> 37000 | D20: =+C20*($H$6/12) -> 109.62963 | E20: =+D20*$E$12 -> 3.837037 | F20: =+D20*$F$12 -> 0.54814815 | G20: =+$G$12 -> 0.5 | H20: =+SUM(D20:G20) -> 114.51481 | I20: =+H20*$I$12 -> 17.177222 | J20: =+H20+I20 -> 131.69204 | M20: =$K$5 -> 101.76804 | N20: =M20-J20 -> -29.923996 | O20: =+O19+N20 -> -246.67686
B21: 8 | C21: =+C20-G$6 -> 36500 | D21: =+C21*($H$6/12) -> 108.14815 | E21: =+D21*$E$12 -> 3.7851852 | F21: =+D21*$F$12 -> 0.54074074 | G21: =+$G$12 -> 0.5 | H21: =+SUM(D21:G21) -> 112.97407 | I21: =+H21*$I$12 -> 16.946111 | J21: =+H21+I21 -> 129.92019 | M21: =$K$5 -> 101.76804 | N21: =M21-J21 -> -28.152144 | O21: =+O20+N21 -> -274.82901
B22: 9 | C22: =+C21-G$6 -> 36000 | D22: =+C22*($H$6/12) -> 106.66667 | E22: =+D22*$E$12 -> 3.7333333 | F22: =+D22*$F$12 -> 0.53333333 | G22: =+$G$12 -> 0.5 | H22: =+SUM(D22:G22) -> 111.43333 | I22: =+H22*$I$12 -> 16.715 | J22: =+H22+I22 -> 128.14833 | M22: =$K$5 -> 101.76804 | N22: =M22-J22 -> -26.380293 | O22: =+O21+N22 -> -301.2093
B23: 10 | C23: =+C22-G$6 -> 35500 | D23: =+C23*($H$6/12) -> 105.18519 | E23: =+D23*$E$12 -> 3.6814815 | F23: =+D23*$F$12 -> 0.52592593 | G23: =+$G$12 -> 0.5 | H23: =+SUM(D23:G23) -> 109.89259 | I23: =+H23*$I$12 -> 16.483889 | J23: =+H23+I23 -> 126.37648 | M23: =$K$5 -> 101.76804 | N23: =M23-J23 -> -24.608441 | O23: =+O22+N23 -> -325.81774
B24: 11 | C24: =+C23-G$6 -> 35000 | D24: =+C24*($H$6/12) -> 103.7037 | E24: =+D24*$E$12 -> 3.6296296 | F24: =+D24*$F$12 -> 0.51851852 | G24: =+$G$12 -> 0.5 | H24: =+SUM(D24:G24) -> 108.35185 | I24: =+H24*$I$12 -> 16.252778 | J24: =+H24+I24 -> 124.60463 | M24: =$K$5 -> 101.76804 | N24: =M24-J24 -> -22.836589 | O24: =+O23+N24 -> -348.65433
B25: 12 | C25: =+C24-G$6 -> 34500 | D25: =+C25*($H$6/12) -> 102.22222 | E25: =+D25*$E$12 -> 3.5777778 | F25: =+D25*$F$12 -> 0.51111111 | G25: =+$G$12 -> 0.5 | H25: =+SUM(D25:G25) -> 106.81111 | I25: =+H25*$I$12 -> 16.021667 | J25: =+H25+I25 -> 122.83278 | M25: =$K$5 -> 101.76804 | N25: =M25-J25 -> -21.064737 | O25: =+O24+N25 -> -369.71907
B26: =IF($D$3>=2,B25+1,"") -> 13 | C26: =IF($D$3>=2,E7,"") -> 34000 | D26: =IF($D$3>=2,C26*($H$7/12),"") -> 99.733333 | E26: =IF($D$3>=2,D26*$E$12,"") -> 3.4906667 | F26: =IF($D$3>=2,D26*$F$12,"") -> 0.49866667 | G26: =IF($D$3>=2,$G$12,"") -> 0.5 | H26: =IF($D$3>=2,SUM(D26:G26),"") -> 104.22267 | I26: =IF($D$3>=2,H26*$I$12,"") -> 15.6334 | J26: =IF($D$3>=2,H26+I26,"") -> 119.85607 | M26: =$K$5 -> 101.76804 | N26: =M26-J26 -> -18.088026 | O26: =IF($D$3>=2,O25+N26,"") -> -387.80709
B27: =IF($D$3>=2,B26+1,"") -> 14 | C27: =IF($D$3>=2,C26-G$7,"") -> 33490 | D27: =IF($D$3>=2,C27*($H$7/12),"") -> 98.237333 | E27: =IF($D$3>=2,D27*$E$12,"") -> 3.4383067 | F27: =IF($D$3>=2,D27*$F$12,"") -> 0.49118667 | G27: =IF($D$3>=2,$G$12,"") -> 0.5 | H27: =IF($D$3>=2,SUM(D27:G27),"") -> 102.66683 | I27: =IF($D$3>=2,H27*$I$12,"") -> 15.400024 | J27: =IF($D$3>=2,H27+I27,"") -> 118.06685 | M27: =$K$5 -> 101.76804 | N27: =M27-J27 -> -16.29881 | O27: =IF($D$3>=2,O26+N27,"") -> -404.1059
B28: =IF($D$3>=2,B27+1,"") -> 15 | C28: =IF($D$3>=2,C27-G$7,"") -> 32980 | D28: =IF($D$3>=2,C28*($H$7/12),"") -> 96.741333 | E28: =IF($D$3>=2,D28*$E$12,"") -> 3.3859467 | F28: =IF($D$3>=2,D28*$F$12,"") -> 0.48370667 | G28: =IF($D$3>=2,$G$12,"") -> 0.5 | H28: =IF($D$3>=2,SUM(D28:G28),"") -> 101.11099 | I28: =IF($D$3>=2,H28*$I$12,"") -> 15.166648 | J28: =IF($D$3>=2,H28+I28,"") -> 116.27763 | M28: =$K$5 -> 101.76804 | N28: =M28-J28 -> -14.509594 | O28: =IF($D$3>=2,O27+N28,"") -> -418.6155
B29: =IF($D$3>=2,B28+1,"") -> 16 | C29: =IF($D$3>=2,C28-G$7,"") -> 32470 | D29: =IF($D$3>=2,C29*($H$7/12),"") -> 95.245333 | E29: =IF($D$3>=2,D29*$E$12,"") -> 3.3335867 | F29: =IF($D$3>=2,D29*$F$12,"") -> 0.47622667 | G29: =IF($D$3>=2,$G$12,"") -> 0.5 | H29: =IF($D$3>=2,SUM(D29:G29),"") -> 99.555147 | I29: =IF($D$3>=2,H29*$I$12,"") -> 14.933272 | J29: =IF($D$3>=2,H29+I29,"") -> 114.48842 | M29: =$K$5 -> 101.76804 | N29: =M29-J29 -> -12.720378 | O29: =IF($D$3>=2,O28+N29,"") -> -431.33588
B30: =IF($D$3>=2,B29+1,"") -> 17 | C30: =IF($D$3>=2,C29-G$7,"") -> 31960 | D30: =IF($D$3>=2,C30*($H$7/12),"") -> 93.749333 | E30: =IF($D$3>=2,D30*$E$12,"") -> 3.2812267 | F30: =IF($D$3>=2,D30*$F$12,"") -> 0.46874667 | G30: =IF($D$3>=2,$G$12,"") -> 0.5 | H30: =IF($D$3>=2,SUM(D30:G30),"") -> 97.999307 | I30: =IF($D$3>=2,H30*$I$12,"") -> 14.699896 | J30: =IF($D$3>=2,H30+I30,"") -> 112.6992 | M30: =$K$5 -> 101.76804 | N30: =M30-J30 -> -10.931162 | O30: =IF($D$3>=2,O29+N30,"") -> -442.26704
B31: =IF($D$3>=2,B30+1,"") -> 18 | C31: =IF($D$3>=2,C30-G$7,"") -> 31450 | D31: =IF($D$3>=2,C31*($H$7/12),"") -> 92.253333 | E31: =IF($D$3>=2,D31*$E$12,"") -> 3.2288667 | F31: =IF($D$3>=2,D31*$F$12,"") -> 0.46126667 | G31: =IF($D$3>=2,$G$12,"") -> 0.5 | H31: =IF($D$3>=2,SUM(D31:G31),"") -> 96.443467 | I31: =IF($D$3>=2,H31*$I$12,"") -> 14.46652 | J31: =IF($D$3>=2,H31+I31,"") -> 110.90999 | M31: =$K$5 -> 101.76804 | N31: =M31-J31 -> -9.141946 | O31: =IF($D$3>=2,O30+N31,"") -> -451.40898
B32: =IF($D$3>=2,B31+1,"") -> 19 | C32: =IF($D$3>=2,C31-G$7,"") -> 30940 | D32: =IF($D$3>=2,C32*($H$7/12),"") -> 90.757333 | E32: =IF($D$3>=2,D32*$E$12,"") -> 3.1765067 | F32: =IF($D$3>=2,D32*$F$12,"") -> 0.45378667 | G32: =IF($D$3>=2,$G$12,"") -> 0.5 | H32: =IF($D$3>=2,SUM(D32:G32),"") -> 94.887627 | I32: =IF($D$3>=2,H32*$I$12,"") -> 14.233144 | J32: =IF($D$3>=2,H32+I32,"") -> 109.12077 | M32: =$K$5 -> 101.76804 | N32: =M32-J32 -> -7.35273 | O32: =IF($D$3>=2,O31+N32,"") -> -458.76171
B33: =IF($D$3>=2,B32+1,"") -> 20 | C33: =IF($D$3>=2,C32-G$7,"") -> 30430 | D33: =IF($D$3>=2,C33*($H$7/12),"") -> 89.261333 | E33: =IF($D$3>=2,D33*$E$12,"") -> 3.1241467 | F33: =IF($D$3>=2,D33*$F$12,"") -> 0.44630667 | G33: =IF($D$3>=2,$G$12,"") -> 0.5 | H33: =IF($D$3>=2,SUM(D33:G33),"") -> 93.331787 | I33: =IF($D$3>=2,H33*$I$12,"") -> 13.999768 | J33: =IF($D$3>=2,H33+I33,"") -> 107.33155 | M33: =$K$5 -> 101.76804 | N33: =M33-J33 -> -5.563514 | O33: =IF($D$3>=2,O32+N33,"") -> -464.32523
B34: =IF($D$3>=2,B33+1,"") -> 21 | C34: =IF($D$3>=2,C33-G$7,"") -> 29920 | D34: =IF($D$3>=2,C34*($H$7/12),"") -> 87.765333 | E34: =IF($D$3>=2,D34*$E$12,"") -> 3.0717867 | F34: =IF($D$3>=2,D34*$F$12,"") -> 0.43882667 | G34: =IF($D$3>=2,$G$12,"") -> 0.5 | H34: =IF($D$3>=2,SUM(D34:G34),"") -> 91.775947 | I34: =IF($D$3>=2,H34*$I$12,"") -> 13.766392 | J34: =IF($D$3>=2,H34+I34,"") -> 105.54234 | M34: =$K$5 -> 101.76804 | N34: =M34-J34 -> -3.774298 | O34: =IF($D$3>=2,O33+N34,"") -> -468.09953
B35: =IF($D$3>=2,B34+1,"") -> 22 | C35: =IF($D$3>=2,C34-G$7,"") -> 29410 | D35: =IF($D$3>=2,C35*($H$7/12),"") -> 86.269333 | E35: =IF($D$3>=2,D35*$E$12,"") -> 3.0194267 | F35: =IF($D$3>=2,D35*$F$12,"") -> 0.43134667 | G35: =IF($D$3>=2,$G$12,"") -> 0.5 | H35: =IF($D$3>=2,SUM(D35:G35),"") -> 90.220107 | I35: =IF($D$3>=2,H35*$I$12,"") -> 13.533016 | J35: =IF($D$3>=2,H35+I35,"") -> 103.75312 | M35: =$K$5 -> 101.76804 | N35: =M35-J35 -> -1.985082 | O35: =IF($D$3>=2,O34+N35,"") -> -470.08461
B36: =IF($D$3>=2,B35+1,"") -> 23 | C36: =IF($D$3>=2,C35-G$7,"") -> 28900 | D36: =IF($D$3>=2,C36*($H$7/12),"") -> 84.773333 | E36: =IF($D$3>=2,D36*$E$12,"") -> 2.9670667 | F36: =IF($D$3>=2,D36*$F$12,"") -> 0.42386667 | G36: =IF($D$3>=2,$G$12,"") -> 0.5 | H36: =IF($D$3>=2,SUM(D36:G36),"") -> 88.664267 | I36: =IF($D$3>=2,H36*$I$12,"") -> 13.29964 | J36: =IF($D$3>=2,H36+I36,"") -> 101.96391 | M36: =$K$5 -> 101.76804 | N36: =M36-J36 -> -0.19586598 | O36: =IF($D$3>=2,O35+N36,"") -> -470.28047
B37: =IF($D$3>=2,B36+1,"") -> 24 | C37: =IF($D$3>=2,C36-G$7,"") -> 28390 | D37: =IF($D$3>=2,C37*($H$7/12),"") -> 83.277333 | E37: =IF($D$3>=2,D37*$E$12,"") -> 2.9147067 | F37: =IF($D$3>=2,D37*$F$12,"") -> 0.41638667 | G37: =IF($D$3>=2,$G$12,"") -> 0.5 | H37: =IF($D$3>=2,SUM(D37:G37),"") -> 87.108427 | I37: =IF($D$3>=2,H37*$I$12,"") -> 13.066264 | J37: =IF($D$3>=2,H37+I37,"") -> 100.17469 | M37: =$K$5 -> 101.76804 | N37: =M37-J37 -> 1.59335 | O37: =IF($D$3>=2,O36+N37,"") -> -468.68712
B38: =IF($D$3>=3,B37+1,"") -> 25 | C38: =IF($D$3>=3,E8,"") -> 27880 | D38: =IF($D$3>=3,C38*($H$8/12),"") -> 81.781333 | E38: =IF($D$3>=3,D38*$E$12,"") -> 2.8623467 | F38: =IF($D$3>=3,D38*$F$12,"") -> 0.40890667 | G38: =IF($D$3>=3,$G$12,"") -> 0.5 | H38: =IF($D$3>=3,SUM(D38:G38),"") -> 85.552587 | I38: =IF($D$3>=3,H38*$I$12,"") -> 12.832888 | J38: =IF($D$3>=3,H38+I38,"") -> 98.385475 | M38: =$K$5 -> 101.76804 | N38: =M38-J38 -> 3.382566 | O38: =IF($D$3>=3,O37+N38,"") -> -465.30456
B39: =IF($D$3>=3,B38+1,"") -> 26 | C39: =IF($D$3>=3,C38-G$8,"") -> 27461.8 | D39: =IF($D$3>=3,C39*($H$8/12),"") -> 80.554613 | E39: =IF($D$3>=3,D39*$E$12,"") -> 2.8194115 | F39: =IF($D$3>=3,D39*$F$12,"") -> 0.40277307 | G39: =IF($D$3>=3,$G$12,"") -> 0.5 | H39: =IF($D$3>=3,SUM(D39:G39),"") -> 84.276798 | I39: =IF($D$3>=3,H39*$I$12,"") -> 12.64152 | J39: =IF($D$3>=3,H39+I39,"") -> 96.918318 | M39: =$K$5 -> 101.76804 | N39: =M39-J39 -> 4.8497231 | O39: =IF($D$3>=3,O38+N39,"") -> -460.45483
B40: =IF($D$3>=3,B39+1,"") -> 27 | C40: =IF($D$3>=3,C39-G$8,"") -> 27043.6 | D40: =IF($D$3>=3,C40*($H$8/12),"") -> 79.327893 | E40: =IF($D$3>=3,D40*$E$12,"") -> 2.7764763 | F40: =IF($D$3>=3,D40*$F$12,"") -> 0.39663947 | G40: =IF($D$3>=3,$G$12,"") -> 0.5 | H40: =IF($D$3>=3,SUM(D40:G40),"") -> 83.001009 | I40: =IF($D$3>=3,H40*$I$12,"") -> 12.450151 | J40: =IF($D$3>=3,H40+I40,"") -> 95.45116 | M40: =$K$5 -> 101.76804 | N40: =M40-J40 -> 6.3168803 | O40: =IF($D$3>=3,O39+N40,"") -> -454.13795
B41: =IF($D$3>=3,B40+1,"") -> 28 | C41: =IF($D$3>=3,C40-G$8,"") -> 26625.4 | D41: =IF($D$3>=3,C41*($H$8/12),"") -> 78.101173 | E41: =IF($D$3>=3,D41*$E$12,"") -> 2.7335411 | F41: =IF($D$3>=3,D41*$F$12,"") -> 0.39050587 | G41: =IF($D$3>=3,$G$12,"") -> 0.5 | H41: =IF($D$3>=3,SUM(D41:G41),"") -> 81.72522 | I41: =IF($D$3>=3,H41*$I$12,"") -> 12.258783 | J41: =IF($D$3>=3,H41+I41,"") -> 93.984003 | M41: =$K$5 -> 101.76804 | N41: =M41-J41 -> 7.7840374 | O41: =IF($D$3>=3,O40+N41,"") -> -446.35392
B42: =IF($D$3>=3,B41+1,"") -> 29 | C42: =IF($D$3>=3,C41-G$8,"") -> 26207.2 | D42: =IF($D$3>=3,C42*($H$8/12),"") -> 76.874453 | E42: =IF($D$3>=3,D42*$E$12,"") -> 2.6906059 | F42: =IF($D$3>=3,D42*$F$12,"") -> 0.38437227 | G42: =IF($D$3>=3,$G$12,"") -> 0.5 | H42: =IF($D$3>=3,SUM(D42:G42),"") -> 80.449431 | I42: =IF($D$3>=3,H42*$I$12,"") -> 12.067415 | J42: =IF($D$3>=3,H42+I42,"") -> 92.516846 | M42: =$K$5 -> 101.76804 | N42: =M42-J42 -> 9.2511945 | O42: =IF($D$3>=3,O41+N42,"") -> -437.10272
B43: =IF($D$3>=3,B42+1,"") -> 30 | C43: =IF($D$3>=3,C42-G$8,"") -> 25789 | D43: =IF($D$3>=3,C43*($H$8/12),"") -> 75.647733 | E43: =IF($D$3>=3,D43*$E$12,"") -> 2.6476707 | F43: =IF($D$3>=3,D43*$F$12,"") -> 0.37823867 | G43: =IF($D$3>=3,$G$12,"") -> 0.5 | H43: =IF($D$3>=3,SUM(D43:G43),"") -> 79.173643 | I43: =IF($D$3>=3,H43*$I$12,"") -> 11.876046 | J43: =IF($D$3>=3,H43+I43,"") -> 91.049689 | M43: =$K$5 -> 101.76804 | N43: =M43-J43 -> 10.718352 | O43: =IF($D$3>=3,O42+N43,"") -> -426.38437
B44: =IF($D$3>=3,B43+1,"") -> 31 | C44: =IF($D$3>=3,C43-G$8,"") -> 25370.8 | D44: =IF($D$3>=3,C44*($H$8/12),"") -> 74.421013 | E44: =IF($D$3>=3,D44*$E$12,"") -> 2.6047355 | F44: =IF($D$3>=3,D44*$F$12,"") -> 0.37210507 | G44: =IF($D$3>=3,$G$12,"") -> 0.5 | H44: =IF($D$3>=3,SUM(D44:G44),"") -> 77.897854 | I44: =IF($D$3>=3,H44*$I$12,"") -> 11.684678 | J44: =IF($D$3>=3,H44+I44,"") -> 89.582532 | M44: =$K$5 -> 101.76804 | N44: =M44-J44 -> 12.185509 | O44: =IF($D$3>=3,O43+N44,"") -> -414.19886
B45: =IF($D$3>=3,B44+1,"") -> 32 | C45: =IF($D$3>=3,C44-G$8,"") -> 24952.6 | D45: =IF($D$3>=3,C45*($H$8/12),"") -> 73.194293 | E45: =IF($D$3>=3,D45*$E$12,"") -> 2.5618003 | F45: =IF($D$3>=3,D45*$F$12,"") -> 0.36597147 | G45: =IF($D$3>=3,$G$12,"") -> 0.5 | H45: =IF($D$3>=3,SUM(D45:G45),"") -> 76.622065 | I45: =IF($D$3>=3,H45*$I$12,"") -> 11.49331 | J45: =IF($D$3>=3,H45+I45,"") -> 88.115375 | M45: =$K$5 -> 101.76804 | N45: =M45-J45 -> 13.652666 | O45: =IF($D$3>=3,O44+N45,"") -> -400.5462
B46: =IF($D$3>=3,B45+1,"") -> 33 | C46: =IF($D$3>=3,C45-G$8,"") -> 24534.4 | D46: =IF($D$3>=3,C46*($H$8/12),"") -> 71.967573 | E46: =IF($D$3>=3,D46*$E$12,"") -> 2.5188651 | F46: =IF($D$3>=3,D46*$F$12,"") -> 0.35983787 | G46: =IF($D$3>=3,$G$12,"") -> 0.5 | H46: =IF($D$3>=3,SUM(D46:G46),"") -> 75.346276 | I46: =IF($D$3>=3,H46*$I$12,"") -> 11.301941 | J46: =IF($D$3>=3,H46+I46,"") -> 86.648218 | M46: =$K$5 -> 101.76804 | N46: =M46-J46 -> 15.119823 | O46: =IF($D$3>=3,O45+N46,"") -> -385.42637
B47: =IF($D$3>=3,B46+1,"") -> 34 | C47: =IF($D$3>=3,C46-G$8,"") -> 24116.2 | D47: =IF($D$3>=3,C47*($H$8/12),"") -> 70.740853 | E47: =IF($D$3>=3,D47*$E$12,"") -> 2.4759299 | F47: =IF($D$3>=3,D47*$F$12,"") -> 0.35370427 | G47: =IF($D$3>=3,$G$12,"") -> 0.5 | H47: =IF($D$3>=3,SUM(D47:G47),"") -> 74.070487 | I47: =IF($D$3>=3,H47*$I$12,"") -> 11.110573 | J47: =IF($D$3>=3,H47+I47,"") -> 85.181061 | M47: =$K$5 -> 101.76804 | N47: =M47-J47 -> 16.58698 | O47: =IF($D$3>=3,O46+N47,"") -> -368.83939
B48: =IF($D$3>=3,B47+1,"") -> 35 | C48: =IF($D$3>=3,C47-G$8,"") -> 23698 | D48: =IF($D$3>=3,C48*($H$8/12),"") -> 69.514133 | E48: =IF($D$3>=3,D48*$E$12,"") -> 2.4329947 | F48: =IF($D$3>=3,D48*$F$12,"") -> 0.34757067 | G48: =IF($D$3>=3,$G$12,"") -> 0.5 | H48: =IF($D$3>=3,SUM(D48:G48),"") -> 72.794699 | I48: =IF($D$3>=3,H48*$I$12,"") -> 10.919205 | J48: =IF($D$3>=3,H48+I48,"") -> 83.713903 | M48: =$K$5 -> 101.76804 | N48: =M48-J48 -> 18.054137 | O48: =IF($D$3>=3,O47+N48,"") -> -350.78526
B49: =IF($D$3>=3,B48+1,"") -> 36 | C49: =IF($D$3>=3,C48-G$8,"") -> 23279.8 | D49: =IF($D$3>=3,C49*($H$8/12),"") -> 68.287413 | E49: =IF($D$3>=3,D49*$E$12,"") -> 2.3900595 | F49: =IF($D$3>=3,D49*$F$12,"") -> 0.34143707 | G49: =IF($D$3>=3,$G$12,"") -> 0.5 | H49: =IF($D$3>=3,SUM(D49:G49),"") -> 71.51891 | I49: =IF($D$3>=3,H49*$I$12,"") -> 10.727836 | J49: =IF($D$3>=3,H49+I49,"") -> 82.246746 | M49: =$K$5 -> 101.76804 | N49: =M49-J49 -> 19.521294 | O49: =IF($D$3>=3,O48+N49,"") -> -331.26396
B50: =IF($D$3>=4,B49+1,"") -> 37 | C50: =IF($D$3>=3,E9,"") -> 22861.6 | D50: =IF($D$3>=4,C50*($H$9/12),"") -> 67.060693 | E50: =IF($D$3>=4,D50*$E$12,"") -> 2.3471243 | F50: =IF($D$3>=4,D50*$F$12,"") -> 0.33530347 | G50: =IF($D$3>=4,$G$12,"") -> 0.5 | H50: =IF($D$3>=4,SUM(D50:G50),"") -> 70.243121 | I50: =IF($D$3>=4,H50*$I$12,"") -> 10.536468 | J50: =IF($D$3>=4,H50+I50,"") -> 80.779589 | M50: =$K$5 -> 101.76804 | N50: =M50-J50 -> 20.988451 | O50: =IF($D$3>=4,O49+N50,"") -> -310.27551
B51: =IF($D$3>=4,B50+1,"") -> 38 | C51: =IF($D$3>=4,C50-G$9,"") -> 22518.676 | D51: =IF($D$3>=4,C51*($H$9/12),"") -> 66.054783 | E51: =IF($D$3>=4,D51*$E$12,"") -> 2.3119174 | F51: =IF($D$3>=4,D51*$F$12,"") -> 0.33027391 | G51: =IF($D$3>=4,$G$12,"") -> 0.5 | H51: =IF($D$3>=4,SUM(D51:G51),"") -> 69.196974 | I51: =IF($D$3>=4,H51*$I$12,"") -> 10.379546 | J51: =IF($D$3>=4,H51+I51,"") -> 79.57652 | M51: =$K$5 -> 101.76804 | N51: =M51-J51 -> 22.19152 | O51: =IF($D$3>=4,O50+N51,"") -> -288.08399
B52: =IF($D$3>=4,B51+1,"") -> 39 | C52: =IF($D$3>=4,C51-G$9,"") -> 22175.752 | D52: =IF($D$3>=4,C52*($H$9/12),"") -> 65.048873 | E52: =IF($D$3>=4,D52*$E$12,"") -> 2.2767105 | F52: =IF($D$3>=4,D52*$F$12,"") -> 0.32524436 | G52: =IF($D$3>=4,$G$12,"") -> 0.5 | H52: =IF($D$3>=4,SUM(D52:G52),"") -> 68.150827 | I52: =IF($D$3>=4,H52*$I$12,"") -> 10.222624 | J52: =IF($D$3>=4,H52+I52,"") -> 78.373452 | M52: =$K$5 -> 101.76804 | N52: =M52-J52 -> 23.394589 | O52: =IF($D$3>=4,O51+N52,"") -> -264.6894
B53: =IF($D$3>=4,B52+1,"") -> 40 | C53: =IF($D$3>=4,C52-G$9,"") -> 21832.828 | D53: =IF($D$3>=4,C53*($H$9/12),"") -> 64.042962 | E53: =IF($D$3>=4,D53*$E$12,"") -> 2.2415037 | F53: =IF($D$3>=4,D53*$F$12,"") -> 0.32021481 | G53: =IF($D$3>=4,$G$12,"") -> 0.5 | H53: =IF($D$3>=4,SUM(D53:G53),"") -> 67.104681 | I53: =IF($D$3>=4,H53*$I$12,"") -> 10.065702 | J53: =IF($D$3>=4,H53+I53,"") -> 77.170383 | M53: =$K$5 -> 101.76804 | N53: =M53-J53 -> 24.597658 | O53: =IF($D$3>=4,O52+N53,"") -> -240.09174
B54: =IF($D$3>=4,B53+1,"") -> 41 | C54: =IF($D$3>=4,C53-G$9,"") -> 21489.904 | D54: =IF($D$3>=4,C54*($H$9/12),"") -> 63.037052 | E54: =IF($D$3>=4,D54*$E$12,"") -> 2.2062968 | F54: =IF($D$3>=4,D54*$F$12,"") -> 0.31518526 | G54: =IF($D$3>=4,$G$12,"") -> 0.5 | H54: =IF($D$3>=4,SUM(D54:G54),"") -> 66.058534 | I54: =IF($D$3>=4,H54*$I$12,"") -> 9.9087801 | J54: =IF($D$3>=4,H54+I54,"") -> 75.967314 | M54: =$K$5 -> 101.76804 | N54: =M54-J54 -> 25.800727 | O54: =IF($D$3>=4,O53+N54,"") -> -214.29102
B55: =IF($D$3>=4,B54+1,"") -> 42 | C55: =IF($D$3>=4,C54-G$9,"") -> 21146.98 | D55: =IF($D$3>=4,C55*($H$9/12),"") -> 62.031141 | E55: =IF($D$3>=4,D55*$E$12,"") -> 2.1710899 | F55: =IF($D$3>=4,D55*$F$12,"") -> 0.31015571 | G55: =IF($D$3>=4,$G$12,"") -> 0.5 | H55: =IF($D$3>=4,SUM(D55:G55),"") -> 65.012387 | I55: =IF($D$3>=4,H55*$I$12,"") -> 9.751858 | J55: =IF($D$3>=4,H55+I55,"") -> 74.764245 | M55: =$K$5 -> 101.76804 | N55: =M55-J55 -> 27.003796 | O55: =IF($D$3>=4,O54+N55,"") -> -187.28722
B56: =IF($D$3>=4,B55+1,"") -> 43 | C56: =IF($D$3>=4,C55-G$9,"") -> 20804.056 | D56: =IF($D$3>=4,C56*($H$9/12),"") -> 61.025231 | E56: =IF($D$3>=4,D56*$E$12,"") -> 2.1358831 | F56: =IF($D$3>=4,D56*$F$12,"") -> 0.30512615 | G56: =IF($D$3>=4,$G$12,"") -> 0.5 | H56: =IF($D$3>=4,SUM(D56:G56),"") -> 63.96624 | I56: =IF($D$3>=4,H56*$I$12,"") -> 9.594936 | J56: =IF($D$3>=4,H56+I56,"") -> 73.561176 | M56: =$K$5 -> 101.76804 | N56: =M56-J56 -> 28.206864 | O56: =IF($D$3>=4,O55+N56,"") -> -159.08036
B57: =IF($D$3>=4,B56+1,"") -> 44 | C57: =IF($D$3>=4,C56-G$9,"") -> 20461.132 | D57: =IF($D$3>=4,C57*($H$9/12),"") -> 60.019321 | E57: =IF($D$3>=4,D57*$E$12,"") -> 2.1006762 | F57: =IF($D$3>=4,D57*$F$12,"") -> 0.3000966 | G57: =IF($D$3>=4,$G$12,"") -> 0.5 | H57: =IF($D$3>=4,SUM(D57:G57),"") -> 62.920093 | I57: =IF($D$3>=4,H57*$I$12,"") -> 9.438014 | J57: =IF($D$3>=4,H57+I57,"") -> 72.358107 | M57: =$K$5 -> 101.76804 | N57: =M57-J57 -> 29.409933 | O57: =IF($D$3>=4,O56+N57,"") -> -129.67042
B58: =IF($D$3>=4,B57+1,"") -> 45 | C58: =IF($D$3>=4,C57-G$9,"") -> 20118.208 | D58: =IF($D$3>=4,C58*($H$9/12),"") -> 59.01341 | E58: =IF($D$3>=4,D58*$E$12,"") -> 2.0654694 | F58: =IF($D$3>=4,D58*$F$12,"") -> 0.29506705 | G58: =IF($D$3>=4,$G$12,"") -> 0.5 | H58: =IF($D$3>=4,SUM(D58:G58),"") -> 61.873947 | I58: =IF($D$3>=4,H58*$I$12,"") -> 9.281092 | J58: =IF($D$3>=4,H58+I58,"") -> 71.155039 | M58: =$K$5 -> 101.76804 | N58: =M58-J58 -> 30.613002 | O58: =IF($D$3>=4,O57+N58,"") -> -99.05742
B59: =IF($D$3>=4,B58+1,"") -> 46 | C59: =IF($D$3>=4,C58-G$9,"") -> 19775.284 | D59: =IF($D$3>=4,C59*($H$9/12),"") -> 58.0075 | E59: =IF($D$3>=4,D59*$E$12,"") -> 2.0302625 | F59: =IF($D$3>=4,D59*$F$12,"") -> 0.2900375 | G59: =IF($D$3>=4,$G$12,"") -> 0.5 | H59: =IF($D$3>=4,SUM(D59:G59),"") -> 60.8278 | I59: =IF($D$3>=4,H59*$I$12,"") -> 9.12417 | J59: =IF($D$3>=4,H59+I59,"") -> 69.95197 | M59: =$K$5 -> 101.76804 | N59: =M59-J59 -> 31.816071 | O59: =IF($D$3>=4,O58+N59,"") -> -67.241349
B60: =IF($D$3>=4,B59+1,"") -> 47 | C60: =IF($D$3>=4,C59-G$9,"") -> 19432.36 | D60: =IF($D$3>=4,C60*($H$9/12),"") -> 57.001589 | E60: =IF($D$3>=4,D60*$E$12,"") -> 1.9950556 | F60: =IF($D$3>=4,D60*$F$12,"") -> 0.28500795 | G60: =IF($D$3>=4,$G$12,"") -> 0.5 | H60: =IF($D$3>=4,SUM(D60:G60),"") -> 59.781653 | I60: =IF($D$3>=4,H60*$I$12,"") -> 8.9672479 | J60: =IF($D$3>=4,H60+I60,"") -> 68.748901 | M60: =$K$5 -> 101.76804 | N60: =M60-J60 -> 33.01914 | O60: =IF($D$3>=4,O59+N60,"") -> -34.222209
B61: =IF($D$3>=4,B60+1,"") -> 48 | C61: =IF($D$3>=4,C60-G$9,"") -> 19089.436 | D61: =IF($D$3>=4,C61*($H$9/12),"") -> 55.995679 | E61: =IF($D$3>=4,D61*$E$12,"") -> 1.9598488 | F61: =IF($D$3>=4,D61*$F$12,"") -> 0.27997839 | G61: =IF($D$3>=4,$G$12,"") -> 0.5 | H61: =IF($D$3>=4,SUM(D61:G61),"") -> 58.735506 | I61: =IF($D$3>=4,H61*$I$12,"") -> 8.8103259 | J61: =IF($D$3>=4,H61+I61,"") -> 67.545832 | M61: =$K$5 -> 101.76804 | N61: =M61-J61 -> 34.222209 | O61: =IF($D$3>=4,O60+N61,"") -> 9.2370556e-13
B62: =IF($D$3>=5,B61+1,"") | C62: =IF($D$3>=4,E10,"") -> 18746.512 | D62: =IF($D$3>=5,C62*($H$10/12),"") | E62: =IF($D$3>=5,D62*$E$12,"") | F62: =IF($D$3>=5,D62*$F$12,"") | G62: =IF($D$3>=5,$G$12,"") | H62: =IF($D$3>=5,SUM(D62:G62),"") | I62: =IF($D$3>=5,H62*$I$12,"") | J62: =IF($D$3>=5,H62+I62,"") | M62: =$K$5 -> 101.76804 | N62: =M62-J62 -> #VALUE! | O62: =IF($D$3>=5,O61+N62,"")
B63: =IF($D$3>=5,B62+1,"") | C63: =IF($D$3>=5,C62-G$10,"") | D63: =IF($D$3>=5,C63*($H$10/12),"") | E63: =IF($D$3>=5,D63*$E$12,"") | F63: =IF($D$3>=5,D63*$F$12,"") | G63: =IF($D$3>=5,$G$12,"") | H63: =IF($D$3>=5,SUM(D63:G63),"") | I63: =IF($D$3>=5,H63*$I$12,"") | J63: =IF($D$3>=5,H63+I63,"") | M63: =$K$5 -> 101.76804 | N63: =M63-J63 -> #VALUE! | O63: =IF($D$3>=5,O62+N63,"")
B64: =IF($D$3>=5,B63+1,"") | C64: =IF($D$3>=5,C63-G$10,"") | D64: =IF($D$3>=5,C64*($H$10/12),"") | E64: =IF($D$3>=5,D64*$E$12,"") | F64: =IF($D$3>=5,D64*$F$12,"") | G64: =IF($D$3>=5,$G$12,"") | H64: =IF($D$3>=5,SUM(D64:G64),"") | I64: =IF($D$3>=5,H64*$I$12,"") | J64: =IF($D$3>=5,H64+I64,"") | M64: =$K$5 -> 101.76804 | N64: =M64-J64 -> #VALUE! | O64: =IF($D$3>=5,O63+N64,"")
B65: =IF($D$3>=5,B64+1,"") | C65: =IF($D$3>=5,C64-G$10,"") | D65: =IF($D$3>=5,C65*($H$10/12),"") | E65: =IF($D$3>=5,D65*$E$12,"") | F65: =IF($D$3>=5,D65*$F$12,"") | G65: =IF($D$3>=5,$G$12,"") | H65: =IF($D$3>=5,SUM(D65:G65),"") | I65: =IF($D$3>=5,H65*$I$12,"") | J65: =IF($D$3>=5,H65+I65,"") | M65: =$K$5 -> 101.76804 | N65: =M65-J65 -> #VALUE! | O65: =IF($D$3>=5,O64+N65,"")
B66: =IF($D$3>=5,B65+1,"") | C66: =IF($D$3>=5,C65-G$10,"") | D66: =IF($D$3>=5,C66*($H$10/12),"") | E66: =IF($D$3>=5,D66*$E$12,"") | F66: =IF($D$3>=5,D66*$F$12,"") | G66: =IF($D$3>=5,$G$12,"") | H66: =IF($D$3>=5,SUM(D66:G66),"") | I66: =IF($D$3>=5,H66*$I$12,"") | J66: =IF($D$3>=5,H66+I66,"") | M66: =$K$5 -> 101.76804 | N66: =M66-J66 -> #VALUE! | O66: =IF($D$3>=5,O65+N66,"")
B67: =IF($D$3>=5,B66+1,"") | C67: =IF($D$3>=5,C66-G$10,"") | D67: =IF($D$3>=5,C67*($H$10/12),"") | E67: =IF($D$3>=5,D67*$E$12,"") | F67: =IF($D$3>=5,D67*$F$12,"") | G67: =IF($D$3>=5,$G$12,"") | H67: =IF($D$3>=5,SUM(D67:G67),"") | I67: =IF($D$3>=5,H67*$I$12,"") | J67: =IF($D$3>=5,H67+I67,"") | M67: =$K$5 -> 101.76804 | N67: =M67-J67 -> #VALUE! | O67: =IF($D$3>=5,O66+N67,"")
B68: =IF($D$3>=5,B67+1,"") | C68: =IF($D$3>=5,C67-G$10,"") | D68: =IF($D$3>=5,C68*($H$10/12),"") | E68: =IF($D$3>=5,D68*$E$12,"") | F68: =IF($D$3>=5,D68*$F$12,"") | G68: =IF($D$3>=5,$G$12,"") | H68: =IF($D$3>=5,SUM(D68:G68),"") | I68: =IF($D$3>=5,H68*$I$12,"") | J68: =IF($D$3>=5,H68+I68,"") | M68: =$K$5 -> 101.76804 | N68: =M68-J68 -> #VALUE! | O68: =IF($D$3>=5,O67+N68,"")
B69: =IF($D$3>=5,B68+1,"") | C69: =IF($D$3>=5,C68-G$10,"") | D69: =IF($D$3>=5,C69*($H$10/12),"") | E69: =IF($D$3>=5,D69*$E$12,"") | F69: =IF($D$3>=5,D69*$F$12,"") | G69: =IF($D$3>=5,$G$12,"") | H69: =IF($D$3>=5,SUM(D69:G69),"") | I69: =IF($D$3>=5,H69*$I$12,"") | J69: =IF($D$3>=5,H69+I69,"") | M69: =$K$5 -> 101.76804 | N69: =M69-J69 -> #VALUE! | O69: =IF($D$3>=5,O68+N69,"")
B70: =IF($D$3>=5,B69+1,"") | C70: =IF($D$3>=5,C69-G$10,"") | D70: =IF($D$3>=5,C70*($H$10/12),"") | E70: =IF($D$3>=5,D70*$E$12,"") | F70: =IF($D$3>=5,D70*$F$12,"") | G70: =IF($D$3>=5,$G$12,"") | H70: =IF($D$3>=5,SUM(D70:G70),"") | I70: =IF($D$3>=5,H70*$I$12,"") | J70: =IF($D$3>=5,H70+I70,"") | M70: =$K$5 -> 101.76804 | N70: =M70-J70 -> #VALUE! | O70: =IF($D$3>=5,O69+N70,"")
B71: =IF($D$3>=5,B70+1,"") | C71: =IF($D$3>=5,C70-G$10,"") | D71: =IF($D$3>=5,C71*($H$10/12),"") | E71: =IF($D$3>=5,D71*$E$12,"") | F71: =IF($D$3>=5,D71*$F$12,"") | G71: =IF($D$3>=5,$G$12,"") | H71: =IF($D$3>=5,SUM(D71:G71),"") | I71: =IF($D$3>=5,H71*$I$12,"") | J71: =IF($D$3>=5,H71+I71,"") | M71: =$K$5 -> 101.76804 | N71: =M71-J71 -> #VALUE! | O71: =IF($D$3>=5,O70+N71,"")
B72: =IF($D$3>=5,B71+1,"") | C72: =IF($D$3>=5,C71-G$10,"") | D72: =IF($D$3>=5,C72*($H$10/12),"") | E72: =IF($D$3>=5,D72*$E$12,"") | F72: =IF($D$3>=5,D72*$F$12,"") | G72: =IF($D$3>=5,$G$12,"") | H72: =IF($D$3>=5,SUM(D72:G72),"") | I72: =IF($D$3>=5,H72*$I$12,"") | J72: =IF($D$3>=5,H72+I72,"") | M72: =$K$5 -> 101.76804 | N72: =M72-J72 -> #VALUE! | O72: =IF($D$3>=5,O71+N72,"")
B73: =IF($D$3>=5,B72+1,"") | C73: =IF($D$3>=5,C72-G$10,"") | D73: =IF($D$3>=5,C73*($H$10/12),"") | E73: =IF($D$3>=5,D73*$E$12,"") | F73: =IF($D$3>=5,D73*$F$12,"") | G73: =IF($D$3>=5,$G$12,"") | H73: =IF($D$3>=5,SUM(D73:G73),"") | I73: =IF($D$3>=5,H73*$I$12,"") | J73: =IF($D$3>=5,H73+I73,"") | M73: =$K$5 -> 101.76804 | N73: =M73-J73 -> #VALUE! | O73: =IF($D$3>=5,O72+N73,"")

Sheet PARAMETRIZACIÓN
B8: TASA | C8: TIPO SINIESTRALIDAD | D8: RIESGO | E8: RIESGO MODELO | F8: MONTO ASEGURADO | G8: RIESGO CIUDADES | H8: RIESGO GENERO | I8: RIESGO USO | J8: COLOR | K8: ESTADO CIVIL | L8: EDAD
B9: 0.042 | C9: ALTA | D9: 1 | E9: Chevrolet Sail, Chevrolet Aveo, Chevrolet D-Max, Grand Vitara Kia Sportage, Hyundai Tucson, Hyundai Accent, Kia Rio Nissan Sentra, Suzuki Vitara SZ, Mitsubishi Montero, MAZDA BT50, AMAROK, F150 | F9: 0 A 20000 | G9: Guayaquil, Quito, Santo Domingo, Babahoyo, Quevedo, La Maná, Manta, Chone, Portoviejo, Quito, Machala | H9: HOMBRE 85% | I9: COMERCIAL | J9: NEGRO, AMARILLO TAXI, MARRON, AZUL, VERDE | K9: SOLTERO/A | L9: 16 A 25
B10: 0.036 | C10: MODERADA | D10: 2 | E10: Volkswagen T-Cross, Volkswagen Nuevo Virtus, Volkswagen Nivus, Toyota Corolla,Nissan Qashqai, Mistubishi Outlander, KIA K3/K3 Cross, Chevrolet Tracker | F10: 20001 A 30000 | G10: Cuenca, Ambato, Ibarra, Riobamba, Latacunga, Guaranda | H10: MUJER 15% | I10: PARTICULAR | J10: ROJO, AZUL, GRIS OSCURO | K10: CASADO/A | L10: 25 A 44
B11: 0.029 | C11: BAJA | D11: 3 | E11: Volvo, BMW, Mercedes-Benz, Audi, HONDA, SUBARU, BYD, GEELY, Volkswagen Passat, Mazda CX-80, Audi Q6 e-tron, Zeekr X, Maxus eTERRON 9 | F11: 30001 EN ADELANTE | G11: Loja, Tulcan, Baños, Tena, Galapagos | H11: TERCERA EDAD | I11: CORPORATIVO | J11: BLANCO , PLATA | L11: 45 EN ADELANTE
B16: TASA | C16: TIEMPO DE CRÉDITO | D16: RIESGO MARCAS | E16: RIESGO CIUDADES | F16: RIESGO GENERO | G16: RIESGO USO
B17: 0.036 | C17: HASTA 2 AÑOS | D17: 1 | E17: 1 | F17: 1 | G17: 1
B18: 0.034 | C18: HASTA 2 AÑOS | D18: 2 | E18: 2 | F18: 2 | G18: 2
B19: 0.032 | C19: HASTA 2 AÑOS | D19: 3 | E19: 3 | F19: 3 | G19: 3
B20: 0.035 | C20: HASTA 3 A 5 AÑOS | D20: 1 | E20: 1 | F20: 1 | G20: 1
B21: 0.033 | C21: HASTA 3 A 5 AÑOS | D21: 2 | E21: 2 | F21: 2 | G21: 2
B22: 0.031 | C22: HASTA 3 A 5 AÑOS | D22: 3 | E22: 3 | F22: 3 | G22: 3
B26: TIPO | C26: DEPRECIACIÓN
B27: NUEVO PRIMER AÑO | C27: 0.1
B28: NUEVO A PARTIR DEL SEGUNDO AÑO | C28: 0.15
B29: USADO PRIMER AÑO | C29: 0.15
B30: USADO A PARTIR DEL SEGUNDO AÑO | C30: 0.18
B34: RIESGO | C34: PÉRDIDAS PARCIALES | D34: PÉRDIDAS TOTALES
B35: ALTO | C35: 20% DEL VALOR DEL SINIESTRO MÍNIMO 700 | D35: 20% DEL VALOR ASEGURADO
B36: MODERADO | C36: 15% DEL VALOR DEL SINIESTRO MÍNIMO 500 | D36: 18% DEL VALOR ASEGURADO
B37: BAJO | C37: 10% DEL VALOR DEL SINIESTRO MÍNIMO 300 | D37: 15% DEL VALOR ASEGURADO

Sheet RIESGO - MARCAS
A1: RIESGO
A2: 1 | B2: SINIESTRALIDAD ALTA
B3: Chevrolet: Es la marca más afectada por robos en el país. Modelos como el Aveo, Sail y la camioneta D-Max lideran los reportes de sustracción y colisiones. [1, 2]
B4: Kia: Segunda marca con mayor incidencia de robos. El modelo Sportage se encuentra catalogado como vehículo de alto riesgo por las aseguradoras. [1, 2, 3]
B5: Hyundai: Ocupa el tercer lugar en robos y partes comerciales. El modelo Tucson registra altas tasas de siniestros por delincuencia y accidentes. [1, 2]
B6: Toyota: Aunque cuenta con una excelente reputación en seguridad pasiva, sus modelos Hilux y Fortuner sufren un riesgo crítico de robo a mano armada y desmantelamiento de accesorios
A8: 2 | B8: SINIESTRALIDAD MODERADA
B9: Nissan y Suzuki: Modelos específicos como el Nissan Sentra o el Suzuki Vitara SZ entran continuamente en los listados de autos robados o colisionados. [1]
B10: Mazda: Las camionetas de la serie BT-50 son altamente cotizadas por la delincuencia en zonas rurales, elevando su tasa de riesgo. [1, 2]
B11: Mitsubishi: Vehículos SUV como el Montero registran siniestros frecuentes de pérdida parcial o robo de autopartes. [1, 2]
B12: Ford y Volkswagen: Marcas cuyos vehículos familiares y camionetas (Amarok, F150) sufren siniestros moderados, controlados en parte por sus avanzados sistemas de seguridad activa.
A14: 3 | B14: BAJA SINIESTRALIDAD
B15: Marcas Premium (Volvo, BMW, Mercedes-Benz, Audi): Tienen las tasas de siniestralidad por robo más bajas. Modelos como el Volvo XC60 destacan frecuentemente en seguridad internacional.
B16: Marcas de nicho (Honda, Subaru): Vehículos con una base de usuarios reducida que limita el interés de las mafias de autopartes.
B17: Firmas Chinas Nuevas o Eléctricas (BYD, Geely): Al incorporar tecnologías recientes de software cerrado y baterías complejas, su índice de robo actual es mínimo

Sheet RIESGO - CIUDADES
A1: RIESGO
A2: 1 | B2: ALTA SINIESTRALIDAD
B3: Guayaquil: Lidera el riesgo a nivel nacional. Registra la mayor cantidad de siniestros viales y es el punto crítico para las aseguradoras por robo de vehículos a mano armada y desmantelamiento de autopartes en zonas comerciales. [1, 2, 3, 4, 5]
B4: Quito: Presenta la tasa de mortalidad por accidentes de tránsito más alta en proporción y empata con Guayaquil en volumen de robos de vehículos (aproximadamente uno cada 3.5 horas). Las pólizas aquí exigen casi obligatoriamente un dispositivo GPS. [1, 2, 3]
B5: Santo Domingo: Al ser el eje vial conector del país, registra una altísima siniestralidad por choques pesados y pérdida de pista. Además, ha visto un incremento crítico en robos de camionetas y transporte pesado. [1, 2]
B6: Quevedo y Babahoyo: Ciudades de alta peligrosidad delictiva. Para el sector asegurador, representan zonas de "alerta roja" por la frecuencia de asaltos en ejes viales y robo total de automotores
A8: 2 | B8: SINIESTRALIDAD MODERADA
B9: Cuenca: Aunque registra accidentes urbanos con regularidad, mantiene niveles de robo vehicular sustancialmente más bajos que Quito y Guayaquil. Es considerada una ciudad de riesgo controlado para asegurar autos. [1, 2]
B10: Manta y Portoviejo: En Manabí la siniestralidad por accidentes de motocicletas y autos particulares es alta. El robo de accesorios y camionetas mantiene las alertas en nivel medio. [1, 2]
B11: Machala: Registra problemas de delincuencia comunes de la costa que afectan los vehículos parqueados, sumado a choques en las vías de acceso provinciales. [1, 2]
B12: Ambato y Riobamba: Zonas de tránsito andino con siniestros viales vinculados a neblina o carreteras de curvas, pero con tasas de robo residencial y comercial bajas a moderadas.
B13: GUARANDA
A15: 3 | B15: BAJA SINIESTRALIDAD
B16: Loja: Destaca por tener un orden vial estricto dentro de la urbe, baja tasa de accidentes fatales y niveles mínimos de delincuencia organizada enfocada en autos.
B17: Ibarra y Tulcán: Presentan una siniestralidad vial interna baja. No obstante, por su cercanía con la frontera, las aseguradoras vigilan de cerca el contrabando, aunque el robo local común es reducido.
B18: Baños y Tena: Cantones pequeños o de la región amazónica donde el tráfico es leve. Los siniestros son muy puntuales y aislados.
B19: Región Insular (Galápagos): Es la zona con menor siniestralidad de todo el Ecuador. El riesgo de robo vehicular es prácticamente nulo y las velocidades de circulación están fuertemente limitadas

Sheet RIESGO - GENERO
B2: RIESGO
B3: 1 | C3: HOMBRES | D3: 0.85 | E3: HASTA LOS 32
B4: 2 | C4: MUJERES | D4: 0.15

Sheet USO DEL VH
C3: 3 | D3: CORPORATIVO
C4: 2 | D4: PARTICULAR
C5: 1 | D5: COMERCIAL
